simplebook/app.py
simplebook/worker.py
simplebook/wsgi.py
flask_simplebook-0.6.1.dist-info/LICENSE.md
flask_simplebook-0.6.1.dist-info/METADATA
flask_simplebook-0.6.1.dist-info/WHEEL
flask_simplebook-0.6.1.dist-info/top_level.txt
flask_simplebook-0.6.1.dist-info/RECORD
