Metadata-Version: 2.1
Name: flask-simplebook
Version: 0.6.1
Summary: flask app for SimpleBook
Home-page: https://code.librehq.com/ots/mediawiki/SimpleBook
Author: Open Tech Strategies, LLC
Author-email: frankduncan@opentechstrategies.com
Classifier: Programming Language :: Python :: 3
Classifier: License :: OSI Approved :: GNU Affero General Public License v3
Classifier: Operating System :: OS Independent
License-File: LICENSE.md
Requires-Dist: flask
Requires-Dist: rq
